simulator/__init__.py
simulator/_version.py
simulator/errors/ModelError.py
simulator/errors/ParametersError.py
simulator/errors/ScopeError.py
simulator/errors/SimulationError.py
simulator/errors/TableError.py
simulator/errors/__init__.py
simulator/miscs/Parameters.py
simulator/miscs/Scope.py
simulator/miscs/Table.py
simulator/miscs/__init__.py
simulator/miscs/setlogger.py
simulator/miscs/simulation.py
simulator/models/Model.py
simulator/models/__init__.py
simulator/models/electrical/Capacitor.py
simulator/models/electrical/HessActive.py
simulator/models/electrical/HessPassive.py
simulator/models/electrical/HessPassiveElec.py
simulator/models/electrical/IdealVoltageSource.py
simulator/models/electrical/LionBattery.py
simulator/models/electrical/Resistor.py
simulator/models/electrical/ResistorForBattery.py
simulator/models/electrical/ResistorInSeries.py
simulator/models/electrical/ResistorTemp.py
simulator/models/electrical/TResistor.py
simulator/models/electrical/Ultracapacitor.py
simulator/models/electrical/VoltageSourceForBattery.py
simulator/models/electrical/__init__.py
simulator/solver/__init__.py
simulator/solver/test.py
simulator-1.0.3.dist-info/DESCRIPTION.rst
simulator-1.0.3.dist-info/METADATA
simulator-1.0.3.dist-info/RECORD
simulator-1.0.3.dist-info/WHEEL
simulator-1.0.3.dist-info/metadata.json
simulator-1.0.3.dist-info/top_level.txt
