Metadata-Version: 2.0
Name: simulator
Version: 1.0.3
Summary: Electrical Power System Simulator
Home-page: UNKNOWN
Author: Jason Xing Zhang
Author-email: xingz@uvic.ca
License: MIT License
Platform: any
Requires-Dist: numpy
Requires-Dist: pandas
Requires-Dist: requests
